curved_surface_distance/__init__.py
curved_surface_distance/distance.py
curved_surface_distance-0.0.1.dist-info/LICENSE
curved_surface_distance-0.0.1.dist-info/METADATA
curved_surface_distance-0.0.1.dist-info/WHEEL
curved_surface_distance-0.0.1.dist-info/top_level.txt
curved_surface_distance-0.0.1.dist-info/RECORD
