Metadata-Version: 2.1
Name: curved-surface-distance
Version: 0.0.1
Summary: this package can be used to calculate distance between two points in the curved surface
Author-email: Hareeharan Elangovan <Hareeharan1999@gmail.com>
Classifier: Programming Language :: Python :: 3
Classifier: License :: OSI Approved :: MIT License
Classifier: Operating System :: OS Independent
Requires-Python: >=3.7
License-File: LICENSE
